Workbook

Sheet 结论摘要
A1: 中国增程式（REEV）汽车进口白俄罗斯：关税政策专题
A2: 数据截至 2026-09-30｜范围：增程式（串联式混动）乘用车；个人与法人清关；新车与二手车车龄；与俄罗斯对比｜来源以白俄官方网站为主，每条标注来源编号（见“论证与来源”）与可信度
A4: 一、问题与结论
A5: # | B5: 问题 | C5: 结论 | D5: 来源编号 | E5: 可信度
A6: 1 | B6: 增程式在白俄算什么车？ | C6: 自 2026-01-01 起，增程式在联盟税则中单列为 8703 80 000 5（串联式混动），纯电动车为 8703 80 000 3。依据是欧亚经济委员会（EEC）委员会 2025-09-23 第 81 号决定。“电动车”被重新定义为“仅由电动机驱动、不含任何类型混合动力装置”的车辆，所以增程式（如岚图 FREE、理想）不再算电动车，不享受任何电动车优惠。 | D6: S01, S26, S11, S13 | E6: 高
A7: 2 | B7: 要交哪些税？税率多少？ | C7: 进口关税为完税价格的 15%，增值税 20%（税基 = 完税价格 + 关税），白俄对乘用车不征消费税，另缴报废税和海关手续费。2025 年增程式还按电动车对待，可享受免关税配额和增值税减免；2026 年起两项都没有了，关税加增值税约为完税价格的 38%（1.15 × 1.20 − 1）。 | D7: S13, S22, S21, S27 | E7: 高
A8: 3 | B8: 个人清关和法人清关有什么不同？ | C8: 关税率和增值税率相同（15% + 20%），个人按“综合海关支付”一次缴清。差别有两点：① 报废税：个人按固定金额缴纳，出厂 ≤3 年 624.92 BYN、>3 年 1,282.02 BYN，与动力类型和排量无关；法人按车辆类型和车龄分档，且混动和电动 M1 类车不适用“优惠税率”（法人具体金额本次未取得）。② 增值税：法人若是增值税纳税人，进口增值税可以作进项抵扣，个人不能。此外，2026 年纯电动车免关税配额（个人 6,200 辆、法人 13,800 辆）与增程式无关，且已用完。 | D8: S18, S24, S19, S03, S25 | E8: 高
A9: 4 | B9: 二手车的车龄会影响关税吗？ | C9: 对增程式来说，关税税率不随车龄变化：8703 80 000 5 统一为 15% 从价，不像燃油车和并联/插电混动那样，个人进口要按车龄（≤3 年、3–5 年、>5 年）和排量套用统一税率。车龄只在三个地方起作用：① 完税价格（旧车价值低，税额按比例下降）；② 个人报废税以出厂满 3 年为界，从 624.92 BYN 升至 1,282.02 BYN；③ 纯电动车“出厂 5 年内免增值税”的规定本来就不适用于增程式。 | D9: S26, S27, S18, S30, S31 | E9: 高
A10: 5 | B10: 能否经亚美尼亚或吉尔吉斯斯坦免税进入白俄？ | C10: 不能。2026 年亚美尼亚、吉尔吉斯斯坦各有 15,000 辆免关税配额，覆盖纯电和增程式（8703 80 000 5）；但享受优惠的增程式不得把占有、使用和处置权转让给俄罗斯、哈萨克斯坦、白俄罗斯的公民或常住居民。白俄自己的 20,000 辆配额只给纯电动车（8703 80 000 3）。 | D10: S16, S23, S28 | E10: 高
A11: 6 | B11: 经俄罗斯等成员国清关后再进白俄呢？ | C11: 联盟内部不再征收关税，但在白俄登记时通常仍需缴纳白俄报废税；在其他成员国已登记满 1 年等情形下，不适用相关条款（2024-11-24 起执行，追溯至 2024-07-01）。而且俄罗斯本身的税费高得多（见“白俄与俄罗斯对比”），经俄清关不划算。 | D11: S20, S19 | E11: 中
A12: 7 | B12: 与俄罗斯有什么不同？ | C12: 关税相同（联盟统一税则，增程式 15%）。差别全在国内税费：① 增值税：白俄 20%，俄罗斯 2026 年起 22%；② 消费税：白俄《税法典》应税消费品清单中没有乘用车；俄罗斯按马力征收，2026 年为：≤90 马力 0，90–150 马力 64，150–200 马力 613，200–300 马力 1004，300–400 马力 1711，>500 马力 1829 卢布/马力；③ 报废税：白俄个人为固定低额；俄罗斯为 2 万卢布基础额乘以系数（按功率、车龄），个人优惠（3,400 / 5,200 卢布）对燃油车限 160 马力以内，对增程式和纯电车只限 80 马力以内（按电机 30 分钟最大功率），所以增程车实际都按商业系数缴纳（例：理想 L7 约 219.4 万卢布；新车 >205.95 千瓦时系数 152，约 304 万卢布）。同一辆新增程车，在俄罗斯的税费约为白俄的 3 倍以上（见“俄罗斯对比测算”）。 | D12: S33, S34, S39, S43, S44, S37, S46, S49 | E12: 高
A14: 二、使用说明
A15: 1. “白俄税费测算”：可以输入新车和不同车龄二手车的完税价格，自动计算个人和法人的应缴税费；“俄罗斯对比测算”：对同一辆车估算俄罗斯的税费。
A16: 2. 蓝色字体为可修改的输入值，黄色底为必须按实际填写的关键假设（汇率、法人报废税、俄罗斯报废税等），黑色为公式。
A17: 3. 本专题的数据均通过搜索引擎检索白俄、俄罗斯官方网站及报关数据库的索引摘要获得（运行环境无法直接打开这些网站）。报关前请用 ГТК 计算器 customs.gov.by/calc 核实。

Sheet 分类与政策变化
A1: 增程式的税则归类与 2025→2026 政策变化
A2: 税则归类决定了适用哪套税费规则，这是后面所有结论的起点
A4: 项目 | B4: 2025 年 | C4: 2026 年起 | D4: 依据 / 说明 | E4: 来源编号 | F4: 可信度
A5: 税则编码 | B5: 2025 年：增程式与纯电动车同在 8703 80 000（仅由电动机驱动），按电动车对待 | C5: 2026 年起：8703 80 000 3 = 纯电动车；8703 80 000 5 = 串联式混动（增程式） | D5: EEC 委员会 2025-09-23 第 81 号决定新设 8703 80 000 3 / 4 / 5 / 8 子目，生效不早于 2026-01-01 | E5: S01, S26 | F5: 高
A6: “电动车”定义 | B6: 包括增程式 | C6: M、MG、N、NG 类中仅由电动机驱动、且不含任何类型混合动力装置的车辆 | D6: 增程式带发动机和发电机，因此被排除 | E6: S01, S13 | F6: 高
A7: 进口关税 | B7: 可使用白俄电动车免关税配额（0%） | C7: 15%（完税价格），2026 年不给增程式配额 | D7: 新设子目统一设为 15%；ГТК：增程式 2025 年可享受关税优惠，2026 年起不再享受 | E7: S13, S26, S27 | F7: 高
A8: 进口增值税 | B8: 按电动车免征（个人进口需出厂 ≤5 年） | C8: 20% | D8: 总统令 2025-12-11 第 428 号：2026-01-01 起 0% 增值税只适用于纯电动车；ГТК：个人进口任何混动车（含增程式）都按 20% 计算 | E8: S11, S02, S13 | F8: 高
A9: 综合影响 | B9: — | C9: 价格上涨约 38% | D9: BelTA：取消增值税优惠 +20%，不再享受配额 +15% 关税，合计 1.15 × 1.20 = 1.38；个人和法人都受影响 | E9: S22, S21 | F9: 高
A10: 消费税 | B10: 无 | C10: 无 | D10: 白俄《税法典》第 150 条应税消费品清单中没有乘用车（与俄罗斯不同） | E10: S39, S40, S22 | F10: 高
A11: 报废税 | B11: 个人 544.5 / 1,089 BYN | C11: 个人 624.92 / 1,282.02 BYN（2026-04-29 起） | D11: 部长会议 2026-04-23 第 195 号决议，整体上调约 7%；M1 类混动和电动车不适用“优惠税率” | E11: S18, S24, S19 | F11: 高
A12: 纯电动车优惠（对照） | B12: — | C12: 关税配额 20,000 辆（个人 6,200 / 法人 13,800），2026-01-22 起，已用完；增值税免征延至 2028-12-31（个人为出厂 ≤5 年的车） | D12: 只适用于 8703 80 000 3，与增程式无关 | E12: S03, S04, S12, S17, S25 | F12: 高
A13: 亚美尼亚、吉尔吉斯斯坦配额（对照） | B13: — | C13: 各 15,000 辆，覆盖纯电和增程式（8703 80 000 5） | D13: 享受优惠的增程式禁止转让给白俄、俄、哈的公民或常住居民，不能作为进入白俄的通道 | E13: S16, S23, S28 | F13: 高

Sheet 个人与法人对比
A1: 增程式进口白俄：个人清关与法人清关对比
A2: 个人指以“自用”名义、按旅客报关单申报；法人指企业商业进口（经销、租赁等）
A4: 项目 | B4: 个人（自用） | C4: 法人（商业进口） | D4: 来源编号 | E4: 可信度
A5: 税则编码 | B5: 8703 80 000 5 | C5: 8703 80 000 5 | D5: S01 | E5: 高
A6: 计税方式 | B6: 按“综合海关支付”一次缴清，含关税和增值税。由于 8703 80 项下车辆不适用按排量计的个人统一税率，实际按 15% + 20% 计算 | C6: 关税、增值税分别计算缴纳 | D6: S13, S30, S32 | E6: 中
A7: 进口关税 | B7: 15% × 完税价格 | C7: 15% × 完税价格 | D7: S26, S22 | E7: 高
A8: 增值税 | B8: 20% × (完税价格 + 关税)，不可抵扣 | C8: 20% × (完税价格 + 关税)；增值税纳税人可作进项抵扣（一般税务规则） | D8: S13, S11 | E8: 高
A9: 消费税 | B9: 无（乘用车不在应税清单内） | C9: 无（乘用车不在应税清单内） | D9: S39, S40 | E9: 高
A10: 报废税 | B10: 固定金额：出厂 ≤3 年 624.92 BYN；>3 年 1,282.02 BYN（不论动力类型和排量） | C10: 按车辆类型和车龄分档；M1 类混动和电动车不适用“优惠税率”；具体金额本次未取得，需查部长会议第 195 号决议或 ГТК | D10: S18, S24, S19, S06 | E10: 高
A11: 海关手续费 | B11: 按总统令第 443 号 | C11: 按总统令第 443 号 | D11: S09 | E11: 中
A12: 电动车免关税配额 | B12: 不适用（配额只给纯电动车，个人 6,200 辆，已用完） | C12: 不适用（配额只给纯电动车，法人 13,800 辆，已用完） | D12: S03, S25 | E12: 高
A13: 增值税减免 | B13: 不适用（纯电动车出厂 ≤5 年才免） | C13: 不适用（法人纯电动车免增值税至 2028-12-31） | D13: S11, S12 | E13: 高
A14: 转让限制 | B14: 增程式不享受优惠，因此不受电动车优惠附带的 3 年转让限制 | C14: — | D14: S13, S29 | E14: 中
A15: 关税加增值税合计（占完税价格） | B15: 38% | C15: 38%（抵扣进项后，法人实际负担约 15% 加报废税等） | D15: S22 | E15: 高
A17: 提示：法人进口新车还涉及车型认证等技术合规要求，不在本次“关税”研究范围内。

Sheet 车龄影响
A1: 二手车车龄对清关税费的影响
A2: “车龄”按出厂日期（с даты выпуска）至报关日计算；表中对比增程式与燃油车或并联混动的不同
A4: 一、增程式（8703 80 000 5）在白俄
A5: 项目 | B5: 出厂 ≤3 年 | C5: 3–5 年 | D5: >5 年 | E5: 说明 | F5: 来源编号 | G5: 可信度
A6: 进口关税（个人 / 法人） | B6: 15% | C6: 15% | D6: 15% | E6: 不按车龄分档，车龄不改变税率 | F6: S26, S27 | G6: 高
A7: 增值税（个人 / 法人） | B7: 20% | C7: 20% | D7: 20% | E7: 不按车龄分档 | F7: S13 | G7: 高
A8: 完税价格 | B8: 成交价（新车最高） | C8: 随折旧降低 | D8: 进一步降低 | E8: 税额 = 税率 × 完税价格，旧车税额按价值同比下降；海关可对申报价格进行核查 | F8: S09 | G8: 中
A9: 个人报废税 | B9: 624.92 BYN | C9: 1,282.02 BYN | D9: 1,282.02 BYN | E9: 以出厂满 3 年为界，约翻倍 | F9: S18, S24 | G9: 高
A10: 法人报废税 | B10: 按类型和车龄分档 | C10: 按类型和车龄分档 | D10: 按类型和车龄分档 | E10: 具体金额本次未取得 | F10: S06, S18 | G10: 中
A11: 纯电动车“出厂 5 年内免增值税” | B11: 不适用 | C11: 不适用 | D11: 不适用 | E11: 只适用于纯电动车 8703 80 000 3 | F11: S11, S25 | G11: 高
A13: 二、对照：燃油车和并联/插电混动（个人进口）
A14: 项目 | B14: 出厂 ≤3 年 | C14: 3–5 年 | D14: >5 年 | E14: 说明 | F14: 来源编号 | G14: 可信度
A15: 个人统一税率（综合海关支付） | B15: 按完税价格的一定比例，且不低于每立方厘米最低额 | C15: 按排量每立方厘米若干欧元 | D15: 按排量每立方厘米若干欧元（高于 3–5 年档） | E15: 车龄和排量对税费影响很大；具体税额见 EEC 理事会第 107 号决定附件 2 表 2（本次未逐项取得） | F15: S30, S31, S32 | G15: 中
A17: 三、增程式在俄罗斯（对照）
A18: 项目 | B18: 出厂 ≤3 年 | C18: 3–5 年 | D18: >5 年 | E18: 说明 | F18: 来源编号 | G18: 可信度
A19: 进口关税 | B19: 15% | C19: 15% | D19: 15% | E19: 与白俄相同（联盟统一税则） | F19: S26 | G19: 高
A20: 报废税 | B20: 按功率、车龄分档（商业税率） | C20: 更高系数 | D20: 更高系数 | E20: 2025-12-01 起与功率挂钩；增程式和纯电车的个人优惠只适用于 ≤80 马力 | F20: S37, S38, S49 | G20: 中
A22: 结论：对增程式而言，车龄不改变税率，只通过“完税价格”和“报废税档位”影响总税费；这一点与燃油车和并联混动（车龄直接决定适用的统一税率）明显不同。

Sheet 白俄与俄罗斯对比
A1: 中国增程式汽车进口：白俄罗斯与俄罗斯对比（新车与二手车）
A2: 关税由联盟统一，差别来自各国国内税费。“核实结果”列说明每项差异如何被确认：两国官方来源 / 多个独立来源一致 / 仅单一来源或未取得
A4: 项目 | B4: 白俄罗斯 | C4: 俄罗斯 | D4: 差异与影响 | E4: 核实结果 | F4: 来源编号 | G4: 可信度
A5: 税则编码与关税 | B5: 8703 80 000 5，15% | C5: 8703 80 000 5，15% | D5: 无差异（联盟统一税则） | E5: 已核实：EEC 委员会第 81 号决定，白俄海关与俄方数据库一致 | F5: S26, S01, S27 | G5: 高
A6: 增值税 | B6: 20% | C6: 22%（2026-01-01 起，2025-11-28 第 425-ФЗ 号联邦法） | D6: 俄罗斯高 2 个百分点；两国税基均为完税价格 + 关税（俄罗斯还要加消费税） | E6: 已核实：白俄海关说明；俄罗斯税务局与 КонсультантПлюс 一致 | F6: S13, S33, S34 | G6: 高
A7: 消费税 | B7: 不征：《税法典》第 150 条应税消费品清单（酒、烟、燃料、机油、电子烟、能量饮料等）中没有乘用车 | C7: 按功率征收（2026，卢布/马力）：≤90 马力 0；90–150：64；150–200：613；200–300：1004；300–400：1711；400–500：未独立核实；>500：1829（2027 年 1902，2028 年 1978） | D7: 差异最明确的一项。增程车功率普遍 >150 马力，例：197 马力 × 613 = 120,761 卢布 | E7: 白俄：财政部与税务部一致；俄罗斯：两家财税媒体一致，90–200 马力档另有 КонсультантПлюс 佐证 | F7: S39, S40, S43, S44, S35 | G7: 高
A8: 个人进口计税方式 | B8: 15% 关税 + 20% 增值税，一次缴清 | C8: 15% 关税 + 消费税 + 22% 增值税，一次缴清；电动机驱动车辆不适用按排量计的统一税率 | D8: 规则同源（EEC 理事会第 107 号决定），俄罗斯多出消费税 | E8: 白俄：海关与 BelTA 的 38% 算法一致；俄罗斯：仅 TKS.RU 说明 | F8: S13, S22, S32, S30 | G8: 中
A9: 报废税：个人 | B9: 固定额：出厂 ≤3 年 624.92 BYN；>3 年 1,282.02 BYN；不论动力类型、排量、功率 | C9: 基础额 2 万卢布 × 系数（按功率、车龄）。个人优惠 3,400 卢布（≤3 年）/ 5,200 卢布（>3 年）：燃油车限 ≤160 马力；增程式和纯电车限 ≤80 马力（按电机 30 分钟最大功率，以车辆证书为准）。超出则按商业系数：例理想 L7（197 马力）约 219.4 万卢布；新车 >205.95 千瓦系数 152（约 304 万卢布） | D9: 最大的差距来源：同一辆增程车，白俄约 625 BYN，俄罗斯可达 200 万–300 万卢布 | E9: 白俄：部长会议第 195 号决议，经 pravo.by 与 BelTA 确认；俄罗斯：КонсультантПлюс、ГАРАНТ、TKS.RU 一致（理想 L7 金额仅见 TKS.RU） | F9: S18, S24, S37, S46, S47, S49 | G9: 高
A10: 报废税：经其他成员国转入 | B10: 自 EAEU 成员国输入的车辆在白俄登记时一般要缴白俄报废税（在成员国登记满 1 年等情形除外） | C10: 2026-04-01 起，个人自白俄、哈萨克斯坦、吉尔吉斯斯坦、亚美尼亚输入的车辆，或用于转售的车辆，按商业规则缴纳 | D10: 两国都封堵了“先在别国清关再转入”的做法 | E10: 各有一条来源 | F10: S20, S45, S48 | G10: 中
A11: 报废税：法人 | B11: 按车辆类型、车龄分档；2025-02-10 平均上调约一倍，官方说明是为与俄罗斯 2025 年起的税率“对齐”；2026-04-29 再上调约 7%；M1 类混动和电动车不适用优惠档 | C11: 商业系数（按功率、车龄），2025-12-01 起加入功率维度 | D11: 白俄法人水平向俄罗斯 2025 年水平靠拢，但俄罗斯 2025-12 以后按功率再次加码 | E11: 白俄法人具体金额仍未取得 | F11: S41, S42, S18, S19, S37 | G11: 中
A12: 电动车优惠 | B12: 纯电动车有关税配额（2026 年 2 万辆，已用完）和增值税减免；增程式没有 | C12: 2026 年无电动车关税配额；增程式没有 | D12: 对增程式，两国都没有优惠 | E12: 已核实 | F12: S03, S16, S28 | G12: 高
A13: 新车 vs 二手车 | B13: 关税、增值税税率不随车龄变化；个人报废税满 3 年约翻倍 | C13: 关税税率不随车龄变化；报废税按车龄采用不同系数（超过 3 年更高），个人优惠额 3,400 → 5,200 卢布 | D13: 两国关税都不随车龄变化，车龄通过报废税起作用 | E13: 已核实 | F13: S27, S18, S37 | G13: 高
A15: 结论：同一辆中国增程车，白俄的税费主要是 15% 关税和 20% 增值税（约为完税价格的 38%），再加几百白俄卢布的报废税；俄罗斯多了按马力征收的消费税、更高的增值税，以及按功率计征、通常达数百万卢布的报废税，总税费约为白俄的 3 倍以上。量化示例见“俄罗斯对比测算”。

Sheet 白俄税费测算
A1: 增程式进口白俄罗斯：税费测算（个人 vs 法人，新车 vs 二手车）
A2: 蓝色为输入，黄色底为必须按实际填写的关键假设，黑色为公式。示例车价为假设值，用来展示车龄如何影响税费；请替换为实际完税价格
B4: 一、通用参数
B5: 汇率 BYN/USD | C5: 3 | G5: 【示例值，非实时汇率】按报关当日白俄国家银行官方汇率填写
B6: 进口关税税率（8703 80 000 5） | C6: 0.15 | G6: EEC 委员会第 81 号决定
B7: 增值税税率 | C7: 0.2 | G7: 2026 年起增程式不再免征
B8: 个人报废税：出厂 ≤3 年（BYN） | C8: 624.92 | G8: 部长会议第 195 号决议，2026-04-29 起
B9: 个人报废税：出厂 >3 年（BYN） | C9: 1282.02 | G9: 同上
B10: 海关手续费（BYN，每辆） | C10: 0 | G10: 依总统令第 443 号，按实际填写
B12: 二、场景输入
B13: 项目 | C13: 新车 | D13: 二手 2 年 | E13: 二手 4 年 | F13: 二手 6 年 | G13: 说明
B14: 车龄（出厂至报关，年） | C14: 0.5 | D14: 2 | E14: 4 | F14: 6 | G14: 按出厂日期计算
B15: 完税价格（USD，含运至联盟关境的运费和保险费） | C15: 35000 | D15: 29000 | E15: 24000 | F15: 19000 | G15: 【假设值】示例车价，仅用于演示
B16: 法人报废税（BYN） | C16: 0 | D16: 0 | E16: 0 | F16: 0 | G16: 本次未取得法人金额，请按第 195 号决议或 ГТК 查询后填写
B18: 三、计算结果（公式）
B19: 项目 | C19: 新车 | D19: 二手 2 年 | E19: 二手 4 年 | F19: 二手 6 年 | G19: 说明
B20: 完税价格（BYN） | C20: =C15*$C$5 -> 105000 | D20: =D15*$C$5 -> 87000 | E20: =E15*$C$5 -> 72000 | F20: =F15*$C$5 -> 57000
B21: 进口关税（BYN） | C21: =C20*$C$6 -> 15750 | D21: =D20*$C$6 -> 13050 | E21: =E20*$C$6 -> 10800 | F21: =F20*$C$6 -> 8550 | G21: 个人、法人相同
B22: 增值税（BYN） | C22: =(C20+C21)*$C$7 -> 24150 | D22: =(D20+D21)*$C$7 -> 20010 | E22: =(E20+E21)*$C$7 -> 16560 | F22: =(F20+F21)*$C$7 -> 13110 | G22: 个人、法人相同
B23: 关税 + 增值税（BYN） | C23: =C21+C22 -> 39900 | D23: =D21+D22 -> 33060 | E23: =E21+E22 -> 27360 | F23: =F21+F22 -> 21660
B24: 关税 + 增值税占完税价格 | C24: =IF(C20=0,0,C23/C20) -> 0.38 | D24: =IF(D20=0,0,D23/D20) -> 0.38 | E24: =IF(E20=0,0,E23/E20) -> 0.38 | F24: =IF(F20=0,0,F23/F20) -> 0.38 | G24: 应为 38.0%，不随车龄变化
B25: 个人：报废税（BYN） | C25: =IF(C14<=3,$C$8,$C$9) -> 624.92 | D25: =IF(D14<=3,$C$8,$C$9) -> 624.92 | E25: =IF(E14<=3,$C$8,$C$9) -> 1282.02 | F25: =IF(F14<=3,$C$8,$C$9) -> 1282.02 | G25: 以出厂满 3 年为界
B26: 个人：应缴合计（BYN） | C26: =C23+C25+$C$10 -> 40524.92 | D26: =D23+D25+$C$10 -> 33684.92 | E26: =E23+E25+$C$10 -> 28642.02 | F26: =F23+F25+$C$10 -> 22942.02
B27: 个人：合计占完税价格 | C27: =IF(C20=0,0,C26/C20) -> 0.38595162 | D27: =IF(D20=0,0,D26/D20) -> 0.38718299 | E27: =IF(E20=0,0,E26/E20) -> 0.39780583 | F27: =IF(F20=0,0,F26/F20) -> 0.40249158
B28: 法人：应缴合计（BYN） | C28: =C23+C16+$C$10 -> 39900 | D28: =D23+D16+$C$10 -> 33060 | E28: =E23+E16+$C$10 -> 27360 | F28: =F23+F16+$C$10 -> 21660 | G28: 法人报废税需手工填写
B29: 法人：其中可抵扣进项增值税（BYN） | C29: =C22 -> 24150 | D29: =D22 -> 20010 | E29: =E22 -> 16560 | F29: =F22 -> 13110 | G29: 仅限增值税纳税人
B30: 法人：抵扣后净税费（BYN） | C30: =C28-C29 -> 15750 | D30: =D28-D29 -> 13050 | E30: =E28-E29 -> 10800 | F30: =F28-F29 -> 8550
B31: 法人：净税费占完税价格 | C31: =IF(C20=0,0,C30/C20) -> 0.15 | D31: =IF(D20=0,0,D30/D20) -> 0.15 | E31: =IF(E20=0,0,E30/E20) -> 0.15 | F31: =IF(F20=0,0,F30/F20) -> 0.15
B32: 个人合计折合（USD） | C32: =IF($C$5=0,0,C26/$C$5) -> 13508.307 | D32: =IF($C$5=0,0,D26/$C$5) -> 11228.307 | E32: =IF($C$5=0,0,E26/$C$5) -> 9547.34 | F32: =IF($C$5=0,0,F26/$C$5) -> 7647.34
A34: 依据：关税 15%（S26, S27）；增值税 20%（S13, S11）；个人报废税（S18, S24）。第 24 行在四个场景中都是 38.0%，说明车龄不改变增程式的关税和增值税税率。

Sheet 俄罗斯对比测算
A1: 同一辆新增程车：俄罗斯与白俄罗斯税费对比（估算）
A2: 俄罗斯报废税 = 基础额 × 系数（系数按功率、车龄查条例表格）；增程式个人进口只有 ≤80 马力才适用优惠额。默认系数取 TKS.RU 报道的理想 L7（197 马力）2026 年金额反推（219.4 万 ÷ 2 万 = 109.7），请按车型替换
B5: 完税价格（USD） | C5: =白俄税费测算!C15 -> 35000 | E5: 取自“白俄税费测算”的新车场景
B6: 汇率 RUB/USD | C6: 80 | E6: 【示例值，非实时汇率】
B7: 功率（马力） | C7: 197 | E7: 消费税按车辆功率；报废税按电机 30 分钟最大功率（以车辆证书为准），两者可能不同
B8: 消费税 400–500 马力档单价（卢布/马力） | C8: 0 | E8: 本档 2026 年单价未独立核实，功率在该档时请手工填写
B9: 车龄（年） | C9: 0.5 | E9: 影响个人优惠额（≤3 年 3,400；>3 年 5,200）和商业系数
B10: 报废税基础额（卢布） | C10: 20000 | E10: 第 1291 号政府决定
B11: 报废税系数（商业） | C11: 109.7 | E11: 按功率、车龄查表；默认值为理想 L7 金额反推；新车 >205.95 千瓦为 152
B12: 俄罗斯增值税税率 | C12: 0.22 | E12: 2026-01-01 起
B13: 关税税率 | C13: 0.15 | E13: 与白俄相同
B15: 俄罗斯（卢布，个人自用进口）
B16: 完税价格 | C16: =C5*C6 -> 2800000
B17: 进口关税 | C17: =C16*C13 -> 420000
B18: 消费税单价（卢布/马力） | C18: =IF(C7<=90,0,IF(C7<=150,64,IF(C7<=200,613,IF(C7<=300,1004,IF(C7<=400,1711,IF(C7<=500,C8,1829)))))) -> 613
B19: 消费税 | C19: =C7*C18 -> 120761
B20: 增值税 | C20: =(C16+C17+C19)*C12 -> 734967.42
B21: 报废税 | C21: =IF(C7<=80,IF(C9<=3,3400,5200),C10*C11) -> 2194000
B22: 俄罗斯应缴合计 | C22: =C17+C19+C20+C21 -> 3469728.4
B23: 俄罗斯合计占完税价格 | C23: =IF(C16=0,0,C22/C16) -> 1.2391887
B25: 白俄罗斯（同一辆车，个人，新车）
B26: 白俄应缴合计（BYN） | C26: =白俄税费测算!C26 -> 40524.92
B27: 白俄合计占完税价格 | C27: =白俄税费测算!C27 -> 0.38595162
B28: 俄罗斯合计占比 ÷ 白俄合计占比（倍） | C28: =IF(C27=0,0,C23/C27) -> 3.2107359
B30: 分项差异（占完税价格）
B31: 项目 | C31: 俄罗斯 | D31: 白俄罗斯
B32: 关税 | C32: =C17/C16 -> 0.15 | D32: =白俄税费测算!C21/白俄税费测算!C20 -> 0.15
B33: 消费税 | C33: =C19/C16 -> 0.043128929 | D33: =0 -> 0
B34: 增值税 | C34: =C20/C16 -> 0.26248836 | D34: =白俄税费测算!C22/白俄税费测算!C20 -> 0.23
B35: 报废税 | C35: =C21/C16 -> 0.78357143 | D35: =白俄税费测算!C25/白俄税费测算!C20 -> 0.005951619
A37: 依据：增值税 22%（S33, S34）；消费税 2026 年档位（S43, S44, S35）；报废税规则、80 马力门槛和系数（S37, S46, S47, S49）；个人进口电动机驱动车辆按 15% + 消费税 + 增值税计（S32）。报废税和消费税是按卢布定额的，汇率输入值会影响俄罗斯的占比。

Sheet 论证与来源
A1: 论证思路与数据来源
A2: 先确定归类，再推出计税方式，最后分析个人/法人、车龄和国别差异；每一步都给出证据和来源
A4: 一、论证链条
A5: 步骤 | B5: 论点 | C5: 证据 | D5: 来源编号 | E5: 推理与说明 | F5: 可信度
A6: 1 | B6: 增程式 2026 年起单独归入 8703 80 000 5，不再算电动车 | C6: ГТК 通告：EEC 委员会 2025-09-23 第 81 号决定细分 8703 80 000；“电动车”仅指不含任何类型混动装置的纯电车；Alta 列出新子目 3 / 4 / 5 / 8，税率均为 15% | D6: S01, S26 | E6: 归类决定适用的规则，所以必须先确定。编码变化后，所有与“电动车”挂钩的优惠自动不再覆盖增程式 | F6: 高
A7: 2 | B7: 增程式的关税为 15%，增值税为 20%，个人和法人一样 | C7: ГТК（2025-12）：个人进口任何混动车（含增程式）按 20% 增值税计算，增程式适用 15% 关税；总统令第 428 号取消混动车的增值税优惠；BelTA 按 1.15 × 1.20 算出涨价 38%，并说明个人和法人都受影响 | D7: S13, S11, S22, S21 | E7: 多个白俄官方来源一致；38% 可以由 15% 和 20% 精确复算，互相印证 | F7: 高
A8: 3 | B8: 车龄不改变增程式的税率 | C8: 8703 80 000 5 只有一个 15% 从价税率，没有按车龄分的子目；个人统一税率（第 107 号决定）是按发动机排量和车龄设计的，而 8703 80 项下车辆按关税 + 增值税计算 | D8: S26, S27, S30, S32 | E8: 所以车龄只能通过完税价格和报废税档位影响总额。这一点对燃油车和并联混动不成立 | F8: 高
A9: 4 | B9: 个人与法人的差别在报废税和增值税抵扣 | C9: 部长会议第 195 号决议：个人 M1 类车报废税为固定额，不论动力类型；法人按类型和车龄分档，混动和电动 M1 车不适用优惠税率。增值税进项抵扣是一般税务规则 | D9: S18, S24, S19 | E9: 法人具体报废税额未取得，测算器中留为输入项 | F9: 中
A10: 5 | B10: 绕道其他成员国的路径基本被封堵 | C10: 亚美尼亚、吉尔吉斯斯坦的配额虽然覆盖增程式，但禁止把优惠车辆转让给白俄、俄、哈的公民或居民；从成员国输入的车辆在白俄仍需缴报废税 | D10: S16, S23, S20 | E10: 政策设计明确防止套利 | F10: 高
A11: 6 | B11: 与俄罗斯相比，白俄对增程式的税负明显更低 | C11: 关税相同；俄罗斯增值税 22%、按马力征收消费税、报废税与功率挂钩，且增程式个人优惠门槛仅 80 马力（理想 L7 例：约 219.4 万卢布） | D11: S33, S39, S43, S37, S46, S49 | E11: 各差异项已逐项核实（见“白俄与俄罗斯对比”的“核实结果”列）；理想 L7 的具体金额只见于 TKS.RU，测算器中可替换 | F11: 高
A13: 二、局限
A14: 1. 运行环境无法直接打开白俄和俄罗斯网站，所有数据都来自搜索引擎的索引摘要；报关前请用 ГТК 计算器 customs.gov.by/calc 核实。
A15: 2. 未取得的数据：白俄法人报废税具体金额、海关手续费金额、俄罗斯 400–500 马力档消费税单价、俄罗斯报废税完整系数表、燃油车个人统一税率的具体数值。
A16: 3. 俄罗斯的计征功率口径（消费税按车辆功率，报废税按电机 30 分钟最大功率）以车辆证书为准，同一车型的两个数值可能不同。
A18: 三、数据来源
A19: 编号 | B19: 发布机构 | C19: 标题 | D19: 来源类型 | E19: URL
A20: S01 | B20: 白俄国家海关委员会(ГТК) | C20: Об изменениях в ТН ВЭД ЕАЭС, касающихся электромобилей и последовательных гибридов（税则中电动车与增程式的变化） | D20: 白俄官方：国家机关 | E20: https://www.customs.gov.by/news/ob-izmeneniyakh-v-tn-ved-eaes-kasayushchikhsya-elektromobiley-i-posledovatelnykh-gibridov/
A21: S02 | B21: 白俄国家海关委员会(ГТК) | C21: Об изменении Указа Президента по вопросам стимулирования использования электромобилей（第428号总统令） | D21: 白俄官方：国家机关 | E21: https://www.customs.gov.by/news/ob-izmenenii-ukaza-prezidenta-respubliki-belarus-po-voprosam-stimulirovaniya-ispolzovaniya-elektromo/
A22: S03 | B22: 白俄国家海关委员会(ГТК) | C22: Об установлении льгот в отношении электромобилей на 2026 год（2026年电动车优惠） | D22: 白俄官方：国家机关 | E22: https://www.customs.gov.by/news/ob-ustanovlenii-lgot-v-otnoshenii-elektromobiley-na-2026-god/
A23: S04 | B23: 白俄国家海关委员会(ГТК) | C23: Об изменении законодательства, регулирующего применение льгот в отношении электромобилей в 2026 году | D23: 白俄官方：国家机关 | E23: https://www.customs.gov.by/news/ob-izmenenii-zakonodatelstva-reguliruyushchego-primenenie-lgot-v-otnoshenii-elektromobiley-v-2026-g-/
A24: S05 | B24: 白俄国家海关委员会(ГТК) | C24: Разъяснение ГТК: как сэкономить на таможенных пошлинах, налогах на электромобиль（电动车适用15%关税） | D24: 白俄官方：国家机关 | E24: https://www.customs.gov.by/news/razyasnenie-gosudarstvennogo-tamozhennogo-komiteta-kak-sekonomit-na-tamozhennykh-poshlinakh-nalogakh/
A25: S06 | B25: 白俄国家海关委员会(ГТК) | C25: Утилизационный сбор（报废税，企业） | D25: 白俄官方：国家机关 | E25: https://www.customs.gov.by/participants-ved/biznesmenam/utilizatsionnyy-sbor/
A26: S07 | B26: 白俄国家海关委员会(ГТК) | C26: Уплата утилизационного сбора физическими лицами（个人缴纳报废税） | D26: 白俄官方：国家机关 | E26: https://www.customs.gov.by/fizicheskim-litsam/uplata-utilizatsionnogo-sbora-fizicheskimi-litsami-dokumenty-podtverzhdayushchie-kategoriyu-transpor/
A27: S08 | B27: 白俄国家海关委员会(ГТК) | C27: Об изменении законодательства, регулирующего порядок уплаты утилизационного сбора（2026-04） | D27: 白俄官方：国家机关 | E27: https://www.customs.gov.by/news/ob-izmenenii-zakonodatelstva-reguliruyushchego-poryadok-uplaty-utilizatsionnogo-sbora/
A28: S09 | B28: 白俄国家海关委员会(ГТК) | C28: Таможенный калькулятор（海关税费计算器） | D28: 白俄官方：国家机关 | E28: https://www.customs.gov.by/calc/
A29: S10 | B29: 白俄国家海关委员会(ГТК) | C29: Ввоз товаров для личного пользования с уплатой таможенных платежей（个人物品纳税进口） | D29: 白俄官方：国家机关 | E29: https://www.customs.gov.by/fizicheskim-litsam/vvoz-tovarov-dlya-lichnogo-polzovaniya-s-uplatoy-tamozhennykh-platezhey/
A30: S11 | B30: 白俄税务部(МНС) | C30: Об исчислении НДС и налога на прибыль в связи с принятием Указа от 11.12.2025 № 428 | D30: 白俄官方：国家机关 | E30: https://nalog.gov.by/clarifications/comments/33567/
... A68: S49 | B68: TKS.RU | C68: Какие модели авто могут пропасть в России из-за новых правил утильсбора（含理想L7示例） | D68: 第三方专业数据库（俄） | E68: https://www.tks.ru/autonews/2025/09/18/0004/kakie-modeli-avto-mogut-propast-v-rossii-iz-za-novyih-pravil-utilsbora/
B70: 白俄官方来源数量 | C70: =COUNTIF(D20:D68,"白俄*") -> 29
B71: 白俄官方来源占比 | C71: =C70/COUNTA(A20:A68) -> 0.59183673
